lightning_toolbox/__init__.py
lightning_toolbox/main.py
lightning_toolbox/utils.py
lightning_toolbox/callbacks/__init__.py
lightning_toolbox/callbacks/objective_buffer/__init__.py
lightning_toolbox/callbacks/objective_buffer/callback.py
lightning_toolbox/callbacks/objective_buffer/buffers/__init__.py
lightning_toolbox/callbacks/objective_buffer/buffers/extremes.py
lightning_toolbox/callbacks/objective_buffer/buffers/markers.py
lightning_toolbox/callbacks/objective_buffer/buffers/random.py
lightning_toolbox/callbacks/objective_buffer/buffers/regular.py
lightning_toolbox/data/__init__.py
lightning_toolbox/data/module.py
lightning_toolbox/data/transforms.py
lightning_toolbox/objective_function/__init__.py
lightning_toolbox/objective_function/objective.py
lightning_toolbox/objective_function/terms.py
lightning_toolbox/sweep/__init__.py
lightning_toolbox/sweep/main.py
lightning_toolbox/sweep/parameters.py
lightning_toolbox/training/__init__.py
lightning_toolbox/training/datastructures.py
lightning_toolbox/training/module.py
lightning_toolbox-0.0.35.dist-info/LICENSE
lightning_toolbox-0.0.35.dist-info/METADATA
lightning_toolbox-0.0.35.dist-info/WHEEL
lightning_toolbox-0.0.35.dist-info/entry_points.txt
lightning_toolbox-0.0.35.dist-info/top_level.txt
lightning_toolbox-0.0.35.dist-info/RECORD
