Metadata-Version: 2.1
Name: lightning-toolbox
Version: 0.0.35
Summary: A collection of utilities for PyTorch Lightning.
Home-page: https://github.com/vahidzee/lightning-toolbox
Author: Vahid Zehtab
Author-email: vahid@zehtab.me
License: MIT
Keywords: artificial intelligence,pytorch lightning,objective functions,regularization
Platform: UNKNOWN
Classifier: Development Status :: 3 - Alpha
Classifier: Intended Audience :: Developers
Classifier: Topic :: Scientific/Engineering :: Artificial Intelligence
Classifier: License :: OSI Approved :: MIT License
Classifier: Programming Language :: Python :: 3.8
Requires-Python: >=3.8
Requires-Dist: torch >=1.9
Requires-Dist: lightning >=1.9.0
Requires-Dist: dypy
Requires-Dist: torchvision
